{"arquivo": "telegram_client.py", "caminho": "eddie-auto-dev/specialized_agents/telegram_client.py", "gpu": 1, "eddie_count": 7, "eddie_linhas": [[45, "raise RuntimeError(\"Telegram bot token must be stored in the repo cofre (eddie/telegram_bot_token)\")"], [48, "if (not chat_id) and os.path.exists(\"/etc/eddie/telegram.env\"):"], [50, "with open(\"/etc/eddie/telegram.env\", \"r\", encoding=\"utf-8\") as f:"], [98, "# If running under systemd the env file may not be loaded; try /etc/eddie/telegram.env"], [99, "if (not bot_token or not chat_id) and os.path.exists(\"/etc/eddie/telegram.env\"):"]], "imports_count": 14, "funcoes_publicas": ["from_env", "from_env", "is_configured"], "linhas_total": 524, "sucesso": true}